module_scripts
