Metadata-Version: 1.0
Name: module-starter-cli
Version: 0.5
Summary: Starter project for deploying module
Home-page: http://github.com/storborg/funniest
Author: Aumit Leon
Author-email: aumitleon@gmail.com
License: MIT
Keywords: Module starter
Platform: UNKNOWN
